AreaVol/__init__.py
AreaVol/threed/cube.py
AreaVol/threed/cuboid.py
AreaVol/threed/prism.py
AreaVol/threed/sphere.py
AreaVol/twod/circle.py
AreaVol/twod/rectangle.py
AreaVol/twod/square.py
AreaVol/twod/triangle.py
areavol-1.0.1.dist-info/METADATA
areavol-1.0.1.dist-info/WHEEL
areavol-1.0.1.dist-info/licenses/LICENSE
areavol-1.0.1.dist-info/RECORD
