Metadata-Version: 2.1
Name: AreaVol
Version: 1.0.1
Summary: Package to calculate are and volume
Project-URL: homepage, https://github.com/RachitVM/AreaVol
Project-URL: changelog, https://github.com/RachitVM/AreaVol/blob/main/ChanelLog.md
Author-email: Rachit Murarka <murarka.10.rachit.v@gmail.com>
License-File: LICENSE
Classifier: License :: OSI Approved :: MIT License
Classifier: Operating System :: OS Independent
Classifier: Programming Language :: Python :: 3
Requires-Python: >=3.7
